mhut/__init__.py
mhut/datautils.py
mhut/pathutils.py
mhut/profutils.py
mhut/testutils.py
mhut/timeutils.py
mhut-1.6.4.data/scripts/pathutils
mhut-1.6.4.dist-info/licenses/LICENSE
mhut-1.6.4.dist-info/METADATA
mhut-1.6.4.dist-info/WHEEL
mhut-1.6.4.dist-info/top_level.txt
mhut-1.6.4.dist-info/RECORD
