Metadata-Version: 2.4
Name: mhut
Version: 1.6.4
Summary: Various utilities by MH that show up often in project use
Author: Mahmud Hassan
Author-email: mhassan1900@users.noreply.github.com
License-Expression: MIT
Requires-Python: >=3.8
License-File: LICENSE
Requires-Dist: numpy
Requires-Dist: pandas
Requires-Dist: pytz
Dynamic: license-file
Dynamic: requires-python
